HashedDB/__init__.py
HashedDB-0.0.3.dist-info/LICENSE.txt
HashedDB-0.0.3.dist-info/METADATA
HashedDB-0.0.3.dist-info/WHEEL
HashedDB-0.0.3.dist-info/top_level.txt
HashedDB-0.0.3.dist-info/RECORD
