Metadata-Version: 2.1
Name: HashedDB
Version: 0.0.3
Summary: Secure Password Databases!
Author: Pigeon Nation
License: MIT
Classifier: Programming Language :: Python :: 3
Classifier: License :: OSI Approved :: MIT License
Classifier: Operating System :: OS Independent
Classifier: Topic :: Security :: Cryptography
License-File: LICENSE.txt
